inventree_wled_stocktree/__init__.py
inventree_wled_stocktree/plugin.py
inventree_wled_stocktree/static/script.js
inventree_wled_stocktree/static/styles.css
inventree_wled_stocktree/templates/dashboard.html
inventree_wled_stocktree-0.5.3.9.dist-info/licenses/LICENSE
inventree_wled_stocktree-0.5.3.9.dist-info/METADATA
inventree_wled_stocktree-0.5.3.9.dist-info/WHEEL
inventree_wled_stocktree-0.5.3.9.dist-info/entry_points.txt
inventree_wled_stocktree-0.5.3.9.dist-info/top_level.txt
inventree_wled_stocktree-0.5.3.9.dist-info/RECORD
