Metadata-Version: 2.4
Name: inventree-wled-stocktree
Version: 0.5.3.9
Summary: Use WLED to locate InvenTree StockLocations and StockItems.
Author-email: Matthias Mair <code@mjmair.com>, Rui Borges <ruiborges206@gmail.com>
License-Expression: MIT
Project-URL: Repository, https://github.com/esperaumbocado/wled-inventree
Project-URL: Bug Tracker, https://github.com/esperaumbocado/wled-inventree/issues
Keywords: inventree,inventree-plugin,inventree-wled-locator
Classifier: Programming Language :: Python :: 3
Classifier: Operating System :: OS Independent
Classifier: Development Status :: 5 - Production/Stable
Classifier: Environment :: Plugins
Classifier: Framework :: Django
Classifier: Intended Audience :: Developers
Classifier: Intended Audience :: Manufacturing
Classifier: Intended Audience :: End Users/Desktop
Classifier: Topic :: Scientific/Engineering
Requires-Python: >=3.9
License-File: LICENSE
Requires-Dist: django
Requires-Dist: requests
Provides-Extra: dev
Requires-Dist: twine; extra == "dev"
Requires-Dist: setuptools; extra == "dev"
Dynamic: license-file
